pypicky/__init__.py
pypicky/__main__.py
pypicky/core.py
pypicky/tests/__init__.py
pypicky/tests/test_basic.py
pypicky-0.6.dist-info/licenses/LICENSE
pypicky-0.6.dist-info/METADATA
pypicky-0.6.dist-info/WHEEL
pypicky-0.6.dist-info/entry_points.txt
pypicky-0.6.dist-info/top_level.txt
pypicky-0.6.dist-info/RECORD
