Metadata-Version: 2.4
Name: pypicky
Version: 0.6
Summary: Run a PyPI server with version requirements applied
Author-email: Thomas Robitaille <thomas.robitaille@gmail.com>
Project-URL: Homepage, https://github.com/astrofrog/pypicky
License-File: LICENSE
Requires-Dist: click
Requires-Dist: requests
Requires-Dist: tornado
Requires-Dist: requirements-parser
Provides-Extra: test
Requires-Dist: pytest; extra == "test"
Dynamic: license-file
